<?xml version="1.0" encoding="UTF-8"?>
<!DOCTYPE mapper PUBLIC "-//mybatis.org//DTD Mapper 3.0//EN" "http://mybatis.org/dtd/mybatis-3-mapper.dtd">
<mapper namespace="com.akqid.zblog.mapper.BCommentMapper">
  <resultMap id="BaseResultMap" type="com.akqid.zblog.vo.BComment">
    <!--
      WARNING - @mbg.generated
      This element is automatically generated by MyBatis Generator, do not modify.
    -->
    <constructor>
      <idArg column="id" javaType="java.lang.String" jdbcType="VARCHAR" />
      <arg column="create_by_id" javaType="java.lang.String" jdbcType="VARCHAR" />
      <arg column="create_by_name" javaType="java.lang.String" jdbcType="VARCHAR" />
      <arg column="create_time" javaType="java.util.Date" jdbcType="TIMESTAMP" />
      <arg column="update_by_id" javaType="java.lang.String" jdbcType="VARCHAR" />
      <arg column="update_by_name" javaType="java.lang.String" jdbcType="VARCHAR" />
      <arg column="update_time" javaType="java.util.Date" jdbcType="TIMESTAMP" />
      <arg column="title" javaType="java.lang.String" jdbcType="VARCHAR" />
      <arg column="content" javaType="java.lang.String" jdbcType="VARCHAR" />
      <arg column="del_flag" javaType="java.lang.String" jdbcType="VARCHAR" />
      <arg column="state" javaType="java.lang.String" jdbcType="VARCHAR" />
    </constructor>
  </resultMap>
  <sql id="Example_Where_Clause">
    <!--
      WARNING - @mbg.generated
      This element is automatically generated by MyBatis Generator, do not modify.
    -->
    <where>
      <foreach collection="oredCriteria" item="criteria" separator="or">
        <if test="criteria.valid">
          <trim prefix="(" prefixOverrides="and" suffix=")">
            <foreach collection="criteria.criteria" item="criterion">
              <choose>
                <when test="criterion.noValue">
                  and ${criterion.condition}
                </when>
                <when test="criterion.singleValue">
                  and ${criterion.condition} #{criterion.value}
                </when>
                <when test="criterion.betweenValue">
                  and ${criterion.condition} #{criterion.value} and #{criterion.secondValue}
                </when>
                <when test="criterion.listValue">
                  and ${criterion.condition}
                  <foreach close=")" collection="criterion.value" item="listItem" open="(" separator=",">
                    #{listItem}
                  </foreach>
                </when>
              </choose>
            </foreach>
          </trim>
        </if>
      </foreach>
    </where>
  </sql>
  <sql id="Update_By_Example_Where_Clause">
    <!--
      WARNING - @mbg.generated
      This element is automatically generated by MyBatis Generator, do not modify.
    -->
    <where>
      <foreach collection="example.oredCriteria" item="criteria" separator="or">
        <if test="criteria.valid">
          <trim prefix="(" prefixOverrides="and" suffix=")">
            <foreach collection="criteria.criteria" item="criterion">
              <choose>
                <when test="criterion.noValue">
                  and ${criterion.condition}
                </when>
                <when test="criterion.singleValue">
                  and ${criterion.condition} #{criterion.value}
                </when>
                <when test="criterion.betweenValue">
                  and ${criterion.condition} #{criterion.value} and #{criterion.secondValue}
                </when>
                <when test="criterion.listValue">
                  and ${criterion.condition}
                  <foreach close=")" collection="criterion.value" item="listItem" open="(" separator=",">
                    #{listItem}
                  </foreach>
                </when>
              </choose>
            </foreach>
          </trim>
        </if>
      </foreach>
    </where>
  </sql>
  <sql id="Base_Column_List">
    <!--
      WARNING - @mbg.generated
      This element is automatically generated by MyBatis Generator, do not modify.
    -->
    id, create_by_id, create_by_name, create_time, update_by_id, update_by_name, update_time, 
    title, content, del_flag, state
  </sql>
  <select id="selectByExample" parameterType="com.akqid.zblog.vo.BCommentExample" resultMap="BaseResultMap">
    <!--
      WARNING - @mbg.generated
      This element is automatically generated by MyBatis Generator, do not modify.
    -->
    select
    <if test="distinct">
      distinct
    </if>
    <include refid="Base_Column_List" />
    from b_comment
    <if test="_parameter != null">
      <include refid="Example_Where_Clause" />
    </if>
    <if test="orderByClause != null">
      order by ${orderByClause}
    </if>
  </select>
  <select id="selectByPrimaryKey" parameterType="java.lang.String" resultMap="BaseResultMap">
    <!--
      WARNING - @mbg.generated
      This element is automatically generated by MyBatis Generator, do not modify.
    -->
    select 
    <include refid="Base_Column_List" />
    from b_comment
    where id = #{id,jdbcType=VARCHAR}
  </select>
  <delete id="deleteByPrimaryKey" parameterType="java.lang.String">
    <!--
      WARNING - @mbg.generated
      This element is automatically generated by MyBatis Generator, do not modify.
    -->
    delete from b_comment
    where id = #{id,jdbcType=VARCHAR}
  </delete>
  <delete id="deleteByExample" parameterType="com.akqid.zblog.vo.BCommentExample">
    <!--
      WARNING - @mbg.generated
      This element is automatically generated by MyBatis Generator, do not modify.
    -->
    delete from b_comment
    <if test="_parameter != null">
      <include refid="Example_Where_Clause" />
    </if>
  </delete>
  <insert id="insert" parameterType="com.akqid.zblog.vo.BComment">
    <!--
      WARNING - @mbg.generated
      This element is automatically generated by MyBatis Generator, do not modify.
    -->
    insert into b_comment (id, create_by_id, create_by_name, 
      create_time, update_by_id, update_by_name, 
      update_time, title, content, 
      del_flag, state)
    values (#{id,jdbcType=VARCHAR}, #{createById,jdbcType=VARCHAR}, #{createByName,jdbcType=VARCHAR}, 
      #{createTime,jdbcType=TIMESTAMP}, #{updateById,jdbcType=VARCHAR}, #{updateByName,jdbcType=VARCHAR}, 
      #{updateTime,jdbcType=TIMESTAMP}, #{title,jdbcType=VARCHAR}, #{content,jdbcType=VARCHAR}, 
      #{delFlag,jdbcType=VARCHAR}, #{state,jdbcType=VARCHAR})
  </insert>
  <insert id="insertSelective" parameterType="com.akqid.zblog.vo.BComment">
    <!--
      WARNING - @mbg.generated
      This element is automatically generated by MyBatis Generator, do not modify.
    -->
    insert into b_comment
    <trim prefix="(" suffix=")" suffixOverrides=",">
      <if test="id != null">
        id,
      </if>
      <if test="createById != null">
        create_by_id,
      </if>
      <if test="createByName != null">
        create_by_name,
      </if>
      <if test="createTime != null">
        create_time,
      </if>
      <if test="updateById != null">
        update_by_id,
      </if>
      <if test="updateByName != null">
        update_by_name,
      </if>
      <if test="updateTime != null">
        update_time,
      </if>
      <if test="title != null">
        title,
      </if>
      <if test="content != null">
        content,
      </if>
      <if test="delFlag != null">
        del_flag,
      </if>
      <if test="state != null">
        state,
      </if>
    </trim>
    <trim prefix="values (" suffix=")" suffixOverrides=",">
      <if test="id != null">
        #{id,jdbcType=VARCHAR},
      </if>
      <if test="createById != null">
        #{createById,jdbcType=VARCHAR},
      </if>
      <if test="createByName != null">
        #{createByName,jdbcType=VARCHAR},
      </if>
      <if test="createTime != null">
        #{createTime,jdbcType=TIMESTAMP},
      </if>
      <if test="updateById != null">
        #{updateById,jdbcType=VARCHAR},
      </if>
      <if test="updateByName != null">
        #{updateByName,jdbcType=VARCHAR},
      </if>
      <if test="updateTime != null">
        #{updateTime,jdbcType=TIMESTAMP},
      </if>
      <if test="title != null">
        #{title,jdbcType=VARCHAR},
      </if>
      <if test="content != null">
        #{content,jdbcType=VARCHAR},
      </if>
      <if test="delFlag != null">
        #{delFlag,jdbcType=VARCHAR},
      </if>
      <if test="state != null">
        #{state,jdbcType=VARCHAR},
      </if>
    </trim>
  </insert>
  <select id="countByExample" parameterType="com.akqid.zblog.vo.BCommentExample" resultType="java.lang.Long">
    <!--
      WARNING - @mbg.generated
      This element is automatically generated by MyBatis Generator, do not modify.
    -->
    select count(*) from b_comment
    <if test="_parameter != null">
      <include refid="Example_Where_Clause" />
    </if>
  </select>
  <update id="updateByExampleSelective" parameterType="map">
    <!--
      WARNING - @mbg.generated
      This element is automatically generated by MyBatis Generator, do not modify.
    -->
    update b_comment
    <set>
      <if test="record.id != null">
        id = #{record.id,jdbcType=VARCHAR},
      </if>
      <if test="record.createById != null">
        create_by_id = #{record.createById,jdbcType=VARCHAR},
      </if>
      <if test="record.createByName != null">
        create_by_name = #{record.createByName,jdbcType=VARCHAR},
      </if>
      <if test="record.createTime != null">
        create_time = #{record.createTime,jdbcType=TIMESTAMP},
      </if>
      <if test="record.updateById != null">
        update_by_id = #{record.updateById,jdbcType=VARCHAR},
      </if>
      <if test="record.updateByName != null">
        update_by_name = #{record.updateByName,jdbcType=VARCHAR},
      </if>
      <if test="record.updateTime != null">
        update_time = #{record.updateTime,jdbcType=TIMESTAMP},
      </if>
      <if test="record.title != null">
        title = #{record.title,jdbcType=VARCHAR},
      </if>
      <if test="record.content != null">
        content = #{record.content,jdbcType=VARCHAR},
      </if>
      <if test="record.delFlag != null">
        del_flag = #{record.delFlag,jdbcType=VARCHAR},
      </if>
      <if test="record.state != null">
        state = #{record.state,jdbcType=VARCHAR},
      </if>
    </set>
    <if test="_parameter != null">
      <include refid="Update_By_Example_Where_Clause" />
    </if>
  </update>
  <update id="updateByExample" parameterType="map">
    <!--
      WARNING - @mbg.generated
      This element is automatically generated by MyBatis Generator, do not modify.
    -->
    update b_comment
    set id = #{record.id,jdbcType=VARCHAR},
      create_by_id = #{record.createById,jdbcType=VARCHAR},
      create_by_name = #{record.createByName,jdbcType=VARCHAR},
      create_time = #{record.createTime,jdbcType=TIMESTAMP},
      update_by_id = #{record.updateById,jdbcType=VARCHAR},
      update_by_name = #{record.updateByName,jdbcType=VARCHAR},
      update_time = #{record.updateTime,jdbcType=TIMESTAMP},
      title = #{record.title,jdbcType=VARCHAR},
      content = #{record.content,jdbcType=VARCHAR},
      del_flag = #{record.delFlag,jdbcType=VARCHAR},
      state = #{record.state,jdbcType=VARCHAR}
    <if test="_parameter != null">
      <include refid="Update_By_Example_Where_Clause" />
    </if>
  </update>
  <update id="updateByPrimaryKeySelective" parameterType="com.akqid.zblog.vo.BComment">
    <!--
      WARNING - @mbg.generated
      This element is automatically generated by MyBatis Generator, do not modify.
    -->
    update b_comment
    <set>
      <if test="createById != null">
        create_by_id = #{createById,jdbcType=VARCHAR},
      </if>
      <if test="createByName != null">
        create_by_name = #{createByName,jdbcType=VARCHAR},
      </if>
      <if test="createTime != null">
        create_time = #{createTime,jdbcType=TIMESTAMP},
      </if>
      <if test="updateById != null">
        update_by_id = #{updateById,jdbcType=VARCHAR},
      </if>
      <if test="updateByName != null">
        update_by_name = #{updateByName,jdbcType=VARCHAR},
      </if>
      <if test="updateTime != null">
        update_time = #{updateTime,jdbcType=TIMESTAMP},
      </if>
      <if test="title != null">
        title = #{title,jdbcType=VARCHAR},
      </if>
      <if test="content != null">
        content = #{content,jdbcType=VARCHAR},
      </if>
      <if test="delFlag != null">
        del_flag = #{delFlag,jdbcType=VARCHAR},
      </if>
      <if test="state != null">
        state = #{state,jdbcType=VARCHAR},
      </if>
    </set>
    where id = #{id,jdbcType=VARCHAR}
  </update>
  <update id="updateByPrimaryKey" parameterType="com.akqid.zblog.vo.BComment">
    <!--
      WARNING - @mbg.generated
      This element is automatically generated by MyBatis Generator, do not modify.
    -->
    update b_comment
    set create_by_id = #{createById,jdbcType=VARCHAR},
      create_by_name = #{createByName,jdbcType=VARCHAR},
      create_time = #{createTime,jdbcType=TIMESTAMP},
      update_by_id = #{updateById,jdbcType=VARCHAR},
      update_by_name = #{updateByName,jdbcType=VARCHAR},
      update_time = #{updateTime,jdbcType=TIMESTAMP},
      title = #{title,jdbcType=VARCHAR},
      content = #{content,jdbcType=VARCHAR},
      del_flag = #{delFlag,jdbcType=VARCHAR},
      state = #{state,jdbcType=VARCHAR}
    where id = #{id,jdbcType=VARCHAR}
  </update>
</mapper>